{
  "$interpreted": {
    "Localization": "羅傑",
    "參謀技能": {
      "_maxCastStack": 1,
      "_startCastStack": 0,
      "動作": "對賦予者的隊伍全體賦予永久h0006s3_A1(本角色血量低於50%後，一魂技能的效果提升50%。)",
      "技能CD": 1,
      "起始CD": 0,
      "類型": "被動參謀"
    },
    "復活魂芯數": 10,
    "技能": {
      "Arrive1": [
        "對施術者冷卻時間加1"
      ],
      "Retreat1": [
        "對施術者{\"Tag\":65540,\"_keyString\":\"1\",\"$type\":\"BattleModel.DirectKillSkillEffect\"}"
      ],
      "S1": [
        "對施術者的對方首位攻擊(攻擊力 x1.5)",
        "對施術者攻擊(目前血量的1 x20%)"
      ],
      "S2": [
        "對施術者的對方首位攻擊(攻擊力 x2.5)",
        "對施術者賦予3回合1層weak(易傷)"
      ],
      "S3": [
        "對施術者的對方首位攻擊(攻擊力 x4)"
      ]
    },
    "技能組": {
      "S1": [
        {
          "CoolDown": 0,
          "技能列表": [
            "施展S1"
          ],
          "條件": [
          ],
          "目標": ""
        }
      ],
      "S2": [
        {
          "CoolDown": 0,
          "技能列表": [
            "施展S2"
          ],
          "條件": [
          ],
          "目標": ""
        }
      ],
      "S3": [
        {
          "CoolDown": 0,
          "技能列表": [
            "施展S3"
          ],
          "條件": [
          ],
          "目標": ""
        }
      ]
    },
    "攻擊力": 60,
    "攻擊力等級調整後": 56,
    "敵人AI": "",
    "消魂設置": {
      "Type1": "S1",
      "Type2": "S2",
      "Type4": "S3"
    },
    "疊盾": 300,
    "疊盾等級調整後": 283,
    "站位": "金位",
    "血量": 300,
    "血量等級調整後": 283,
    "被動Buff": [
      "賦予永久h0006s4_P1(本角色血量低於80%/50%後，一/二魂技能的效果提升50%。)"
    ],
    "起始CD": 0,
    "預設CD": 0
  },
  "$type": "BattleModel.FriendCharacter",
  "ReferenceBuffKeys": [
    "h0006s4_P1",
    "h0006s3_A1",
    "weak"
  ],
  "ReferenceCharacterKeys": [
  ],
  "ReferenceEffectKeys": [
    "b0006s4_s01_dust",
    "h0006s4_s01_Dust",
    "h0006s4_s01_Slash",
    "h0006s4_s02_jump_smoke",
    "Common_SmokeDown03_B",
    "Common_HitDash01_B",
    "h0006s5_S1_blood",
    "h0004s4_s03_Dust",
    "h0006s4_s2_Slash",
    "h0006s4_s02_Slash",
    "h0006s4_s02_ShockWave",
    "t0032s5_s02sp_Slash",
    "Common_SmokeDown03_A",
    "h0006s4_s03_Eyes",
    "h0006s4_s03_Ready",
    "h0006s4_s03_Slash01",
    "h0006s4_s03_Fight",
    "h0006s4_s03_Slash03",
    "Common_HitDash01_A"
  ],
  "ReferenceEmoIconKeys": [
  ],
  "ReferenceMusicKeys": [
  ],
  "ReferenceSFXKeys": [
    "step_shoes_008",
    "swoosh_072",
    "step_shoes_002",
    "swoosh_007",
    "swoosh_056",
    "swoosh_057",
    "swoosh_068",
    "step_shoes_003",
    "impact_body_stab_03",
    "sword_005",
    "swoosh_019",
    "magic_light_015",
    "magic_light_048",
    "sword_002",
    "metal_009",
    "movment_009",
    "magic_light_019"
  ],
  "ReferenceVoiceSFXKeys": [
    "h0006s4_skill_s1_1",
    "h0006s4_skill_s1_2",
    "h0006s4_skill_s2_1",
    "h0006s4_skill_s2_2",
    "h0006s4_skill_s3",
    "h0006_battle_hit_01_2_short_med",
    "h0006_battle_hit_01_3_long_strong"
  ],
  "_armorCapacity": 300,
  "_assistantSkill": {
    "$type": "BattleModel.AssistantPassiveBuffSkill",
    "BuffData": {
      "BuffId": "h0006s3_A1",
      "Forever": false,
      "LevelStack": 0,
      "OverwriteDuration": -1,
      "UserDefineVariable": {
      }
    },
    "PassiveBuffDatas": [
      {
        "BuffData": {
          "BuffId": "h0006s3_A1",
          "Forever": false,
          "LevelStack": 0,
          "OverwriteDuration": -1,
          "UserDefineVariable": {
          }
        },
        "TargetSelector": {
          "IsMultiple": true,
          "multi": {
            "$type": "BattleModel.SelfTeamChars",
            "excludeSelf": false,
            "includeDead": true,
            "includeEmpty": false,
            "reference": {
              "$type": "BattleModel.ThisBuffCaster"
            }
          }
        }
      }
    ],
    "TargetSelector": {
      "IsMultiple": true,
      "multi": {
        "$type": "BattleModel.SelfTeamChars",
        "excludeSelf": false,
        "includeDead": true,
        "includeEmpty": false,
        "reference": {
          "$type": "BattleModel.ThisBuffCaster"
        }
      }
    },
    "_maxCastStack": 1,
    "_skillCD": 1,
    "_skillIcon": 32,
    "_startCD": 0,
    "_startCastStack": 0
  },
  "_bloodCapacity": 300,
  "_characterAI": {
    "$type": "BattleModel.SequenceEnemyAI",
    "OrderList": [
    ]
  },
  "_defaultCoolDown": 0,
  "_initialCoolDown": 0,
  "_levelStartBuff": [
  ],
  "_mass": 1,
  "_masterRank": 0,
  "_passiveBuff": [
    {
      "BuffId": "h0006s4_P1",
      "Forever": false,
      "LevelStack": 0,
      "OverwriteDuration": -1,
      "UserDefineVariable": {
      }
    }
  ],
  "_pose": "Stand",
  "_power": 60,
  "_reviveCount": 10,
  "_skills": {
    "Arrive1": {
      "$type": "BattleModel.BattleSkill",
      "_isFallBackIfEmptyTarget": false,
      "_isResolveTargetEachUnit": false,
      "_skillIdentifiers": [
        {
          "CanBeEmpty": false,
          "IsMultiple": false,
          "multi": null,
          "single": {
            "$type": "BattleModel.ThisSkillCaster"
          },
          "skillEffects": [
            {
              "$type": "BattleModel.ChangeCDSkillEffect",
              "Tag": 1028,
              "_keyString": "",
              "_value": 1
            }
          ]
        }
      ]
    },
    "Retreat1": {
      "$type": "BattleModel.BattleSkill",
      "_isFallBackIfEmptyTarget": false,
      "_isResolveTargetEachUnit": false,
      "_skillIdentifiers": [
        {
          "CanBeEmpty": false,
          "IsMultiple": false,
          "multi": null,
          "single": {
            "$type": "BattleModel.ThisSkillCaster"
          },
          "skillEffects": [
            {
              "$type": "BattleModel.DirectKillSkillEffect",
              "Tag": 65540,
              "_keyString": "1"
            }
          ]
        }
      ]
    },
    "S1": {
      "$type": "BattleModel.BattleSkill",
      "_isFallBackIfEmptyTarget": false,
      "_isResolveTargetEachUnit": false,
      "_skillIdentifiers": [
        {
          "CanBeEmpty": false,
          "IsMultiple": false,
          "multi": null,
          "single": {
            "$type": "BattleModel.FrontOfChars",
            "group": {
              "$type": "BattleModel.OppositeTeamChars",
              "includeDead": false,
              "includeEmpty": false,
              "reference": {
                "$type": "BattleModel.ThisSkillCaster"
              }
            }
          },
          "skillEffects": [
            {
              "$type": "BattleModel.HpDamageSkillEffect",
              "Tag": 9,
              "_keyString": "1",
              "_skillModifier": {
                "_constant": 0,
                "_parameter": {
                  "$type": "BattleModel.SkillCasterPower",
                  "basePower": false
                },
                "_ratio": 1.5
              }
            }
          ]
        },
        {
          "CanBeEmpty": false,
          "IsMultiple": false,
          "multi": null,
          "single": {
            "$type": "BattleModel.ThisSkillCaster"
          },
          "skillEffects": [
            {
              "$type": "BattleModel.HpDamageRatioCurrentSkillEffect",
              "Tag": 32777,
              "_keyString": "2",
              "_skillModifier": {
                "_constant": 0,
                "_parameter": {
                  "$type": "BattleModel.ConstanctInt",
                  "constant": 1
                },
                "_ratio": 0.2
              }
            }
          ]
        }
      ]
    },
    "S2": {
      "$type": "BattleModel.BattleSkill",
      "_isFallBackIfEmptyTarget": false,
      "_isResolveTargetEachUnit": false,
      "_skillIdentifiers": [
        {
          "CanBeEmpty": false,
          "IsMultiple": false,
          "multi": null,
          "single": {
            "$type": "BattleModel.FrontOfChars",
            "group": {
              "$type": "BattleModel.OppositeTeamChars",
              "includeDead": false,
              "includeEmpty": false,
              "reference": {
                "$type": "BattleModel.ThisSkillCaster"
              }
            }
          },
          "skillEffects": [
            {
              "$type": "BattleModel.HpDamageSkillEffect",
              "Tag": 9,
              "_keyString": "1",
              "_skillModifier": {
                "_constant": 0,
                "_parameter": {
                  "$type": "BattleModel.SkillCasterPower",
                  "basePower": false
                },
                "_ratio": 2.5
              }
            }
          ]
        },
        {
          "CanBeEmpty": false,
          "IsMultiple": false,
          "multi": null,
          "single": {
            "$type": "BattleModel.ThisSkillCaster"
          },
          "skillEffects": [
            {
              "$type": "BattleModel.AddBuffSkillEffect",
              "Tag": 132,
              "_buffData": [
                {
                  "BuffId": "weak",
                  "Forever": false,
                  "LevelStack": 1,
                  "OverwriteDuration": 3,
                  "UserDefineVariable": {
                  }
                }
              ],
              "_keyString": "2"
            }
          ]
        }
      ]
    },
    "S3": {
      "$type": "BattleModel.BattleSkill",
      "_isFallBackIfEmptyTarget": false,
      "_isResolveTargetEachUnit": false,
      "_skillIdentifiers": [
        {
          "CanBeEmpty": false,
          "IsMultiple": false,
          "multi": null,
          "single": {
            "$type": "BattleModel.FrontOfChars",
            "group": {
              "$type": "BattleModel.OppositeTeamChars",
              "includeDead": false,
              "includeEmpty": false,
              "reference": {
                "$type": "BattleModel.ThisSkillCaster"
              }
            }
          },
          "skillEffects": [
            {
              "$type": "BattleModel.HpDamageSkillEffect",
              "Tag": 9,
              "_keyString": "1",
              "_skillModifier": {
                "_constant": 0,
                "_parameter": {
                  "$type": "BattleModel.SkillCasterPower",
                  "basePower": false
                },
                "_ratio": 4
              }
            }
          ]
        }
      ]
    }
  },
  "_skillsetTable": {
    "S1": {
      "ComboList": [
        {
          "ConditionList": [
          ],
          "SkillList": [
            {
              "ConditionList": [
              ],
              "SkillID": "S1",
              "_conditionalSequences": [
              ],
              "seq": "",
              "t": null
            }
          ],
          "_characterCoolDown": 0,
          "assignTarget": null,
          "icon": 1
        }
      ],
      "_isViewSkillSet": false
    },
    "S2": {
      "ComboList": [
        {
          "ConditionList": [
          ],
          "SkillList": [
            {
              "ConditionList": [
              ],
              "SkillID": "S2",
              "_conditionalSequences": [
              ],
              "seq": "",
              "t": null
            }
          ],
          "_characterCoolDown": 0,
          "assignTarget": null,
          "icon": 65
        }
      ],
      "_isViewSkillSet": false
    },
    "S3": {
      "ComboList": [
        {
          "ConditionList": [
          ],
          "SkillList": [
            {
              "ConditionList": [
              ],
              "SkillID": "S3",
              "_conditionalSequences": [
              ],
              "seq": "",
              "t": null
            }
          ],
          "_characterCoolDown": 0,
          "assignTarget": null,
          "icon": 1
        }
      ],
      "_isViewSkillSet": false
    }
  },
  "_stoneEraseSetting": [
    {
      "Key": 0,
      "Value": "S1"
    },
    {
      "Key": 1,
      "Value": "S2"
    },
    {
      "Key": 2,
      "Value": "S3"
    }
  ],
  "_stoneType": 1
}